printopia/__init__.py
printopia/printopia.py
printopia-0.4.0.dist-info/METADATA
printopia-0.4.0.dist-info/WHEEL
printopia-0.4.0.dist-info/RECORD
