Metadata-Version: 2.1
Name: printopia
Version: 0.4.0
Summary: 
Author: akshat
Author-email: akshat1997tamrakar@gmail.com
Requires-Python: >=3.9,<4.0
Classifier: Programming Language :: Python :: 3
Classifier: Programming Language :: Python :: 3.9
Classifier: Programming Language :: Python :: 3.10
Classifier: Programming Language :: Python :: 3.11
Requires-Dist: colorama (>=0.4.6,<0.5.0)
